odoo/addons/fs_folder/README.rst
odoo/addons/fs_folder/__init__.py
odoo/addons/fs_folder/__manifest__.py
odoo/addons/fs_folder/fields.py
odoo/addons/fs_folder/fs_stream.py
odoo/addons/fs_folder/controllers/__init__.py
odoo/addons/fs_folder/controllers/fs_folder_controller.py
odoo/addons/fs_folder/i18n/fs_folder.pot
odoo/addons/fs_folder/i18n/it.po
odoo/addons/fs_folder/models/__init__.py
odoo/addons/fs_folder/models/bus_bus.py
odoo/addons/fs_folder/models/fs_folder_field_value_adapter.py
odoo/addons/fs_folder/models/fs_folder_field_web_api.py
odoo/addons/fs_folder/models/fs_storage.py
odoo/addons/fs_folder/models/ir_model_fields.py
odoo/addons/fs_folder/readme/CONTEXT.md
odoo/addons/fs_folder/readme/CONTRIBUTORS.md
odoo/addons/fs_folder/readme/CREDITS.md
odoo/addons/fs_folder/readme/DESCRIPTION.md
odoo/addons/fs_folder/readme/USAGE.md
odoo/addons/fs_folder/static/description/icon.png
odoo/addons/fs_folder/static/description/index.html
odoo/addons/fs_folder/static/src/fs_folder/fs_folder.esm.js
odoo/addons/fs_folder/static/src/fs_folder/fs_folder.scss
odoo/addons/fs_folder/static/src/fs_folder/fs_folder.xml
odoo/addons/fs_folder/static/src/fs_folder/fs_folder_item/fs_folder_item.esm.js
odoo/addons/fs_folder/static/src/fs_folder/fs_folder_item/fs_folder_item.xml
odoo/addons/fs_folder/static/src/fs_service/fs_notification.esm.js
odoo/addons/fs_folder/static/src/fs_service/fs_service.esm.js
odoo/addons/fs_folder/static/src/preview_iframe/preview_iframe.esm.js
odoo/addons/fs_folder/static/src/preview_iframe/preview_iframe.scss
odoo/addons/fs_folder/static/src/preview_iframe/preview_iframe.xml
odoo/addons/fs_folder/static/src/preview_iframe/preview_iframe_hook.esm.js
odoo/addons/fs_folder/static/src/simple_dialog/simple_dialog.esm.js
odoo/addons/fs_folder/static/src/simple_dialog/simple_dialog.xml
odoo/addons/fs_folder/tests/__init__.py
odoo/addons/fs_folder/tests/common.py
odoo/addons/fs_folder/tests/models.py
odoo/addons/fs_folder/tests/test_fields.py
odoo_addon_fs_folder-18.0.1.0.1.2.dist-info/METADATA
odoo_addon_fs_folder-18.0.1.0.1.2.dist-info/WHEEL
odoo_addon_fs_folder-18.0.1.0.1.2.dist-info/top_level.txt
odoo_addon_fs_folder-18.0.1.0.1.2.dist-info/RECORD
