Metadata-Version: 2.1
Name: odoo-addon-fs_folder
Version: 18.0.1.0.1.2
Requires-Python: >=3.10
Requires-Dist: odoo-addon-fs_storage==18.0.*
Requires-Dist: odoo==18.0.*
Summary: A module to link to Odoo records and manage from record forms forlders from external file systems
Home-page: https://github.com/OCA/storage
License: LGPL-3
Author: ACSONE SA/NV,Odoo Community Association (OCA)
Author-email: support@odoo-community.org
Classifier: Programming Language :: Python
Classifier: Framework :: Odoo
Classifier: Framework :: Odoo :: 18.0
Classifier: License :: OSI Approved :: GNU Lesser General Public License v3 (LGPLv3)
